showcase_browser/__init__.py
showcase_browser/args.py
showcase_browser/communicate.py
showcase_browser/main.py
showcase_browser/showcase.py
showcase_browser/versions.py
showcase_browser/webpolicies.py
showcase_browser/__pycache__/__init__.cpython-310.pyc
showcase_browser/__pycache__/args.cpython-310.pyc
showcase_browser/__pycache__/communicate.cpython-310.pyc
showcase_browser/__pycache__/showcase.cpython-310.pyc
showcase_browser/__pycache__/versions.cpython-310.pyc
showcase_browser/__pycache__/webpolicies.cpython-310.pyc
showcase_browser/things/back.png
showcase_browser/things/forward.png
showcase_browser/things/home.png
showcase_browser/things/refresh.png
showcase_browser/things/source.txt
showcase_browser/things/stop.png
showcase_browser/things/tab_add.png
showcase_browser-0.1.3.2.dist-info/LICENSE.txt
showcase_browser-0.1.3.2.dist-info/METADATA
showcase_browser-0.1.3.2.dist-info/WHEEL
showcase_browser-0.1.3.2.dist-info/entry_points.txt
showcase_browser-0.1.3.2.dist-info/top_level.txt
showcase_browser-0.1.3.2.dist-info/RECORD
