Metadata-Version: 2.1
Name: showcase_browser
Version: 0.1.3.2
Summary: Minimalistic Browser / Website to App / Showcase App
Author-email: "Adrian F. Hoefflin" <srccircumflex@outlook.com>
License: GPL v3
Project-URL: Homepage, https://github.com/srccircumflex/ShowCase-Browser
Keywords: ui,giu,app,showcase,browser,minimalistic,website to app
Classifier: Environment :: Console
Classifier: Environment :: Web Environment
Classifier: Environment :: X11 Applications :: Qt
Classifier: Intended Audience :: Developers
Classifier: License :: OSI Approved :: GNU General Public License v3 (GPLv3)
Classifier: Natural Language :: English
Classifier: Programming Language :: Python :: 3.10
Classifier: Programming Language :: Python :: 3.11
Classifier: Programming Language :: Python :: 3.12
Classifier: Programming Language :: Python :: 3.13
Classifier: Programming Language :: Python :: 3.14
Classifier: Topic :: Desktop Environment
Classifier: Topic :: Internet :: WWW/HTTP :: Browsers
Requires-Python: >=3.10
License-File: LICENSE.txt
Requires-Dist: PyQt6 >=6.7.0
Requires-Dist: PyQt6-WebEngine >=6.7.0
